queck/__init__.py
queck/answer_models.py
queck/cli.py
queck/extract.py
queck/gh_alert_mdit.py
queck/live_server.py
queck/model_utils.py
queck/queck_models.py
queck/quiz_models.py
queck/render_utils.py
queck/utils.py
queck/prompts/quiz_extraction_prompt.txt
queck/prompts/quiz_structure.txt
queck/templates/base.css
queck/templates/default.css
queck/templates/hljs_includes.html
queck/templates/katex_includes.html
queck/templates/queck_template.html.jinja
queck/templates/queck_template.md.jinja
queck/templates/queck_template.yaml.jinja
queck-2.1.1.dist-info/licenses/LICENSE
queck-2.1.1.dist-info/METADATA
queck-2.1.1.dist-info/WHEEL
queck-2.1.1.dist-info/entry_points.txt
queck-2.1.1.dist-info/top_level.txt
queck-2.1.1.dist-info/RECORD
