Metadata-Version: 2.4
Name: queck
Version: 2.1.1
Summary: A quiz authoring format and tool with different export formats.
Author-email: Livin Nector <livinnector2001@gmail.com>
License: MIT
Project-URL: github, https://github.com/livinNector/queck
Project-URL: source, https://github.com/livinNector/queck.git
Requires-Python: <4.0,>=3.12
License-File: LICENSE
Requires-Dist: pydantic<3.0,>=2.0
Requires-Dist: jinja2<4.0,>=3.1
Requires-Dist: mdit-py-plugins>=0.4.2
Requires-Dist: linkify-it-py>=2.0.3
Requires-Dist: watchfiles>=0.24.0
Requires-Dist: css-inline>=0.14.1
Requires-Dist: fire>=0.7.0
Requires-Dist: pygments>=2.18.0
Requires-Dist: asyncio>=3.4.3
Requires-Dist: websockets>=13.1
Requires-Dist: mdformat>=0.7.19
Requires-Dist: mdformat-black>=0.1.1
Requires-Dist: mdformat-gfm>=0.3.7
Requires-Dist: ruamel-yaml>=0.18.6
Requires-Dist: mdformat-tables>=1.0.0
Requires-Dist: mdformat-gfm-alerts>=1.0.1
Requires-Dist: mdformat-dollarmath>=0.0.1
Requires-Dist: ipython~=8.0
Requires-Dist: yamlfix>=1.17.0
Requires-Dist: mdformat-simple-breaks>=0.0.1
Provides-Extra: genai
Requires-Dist: langchain-groq>=0.3.2; extra == "genai"
Requires-Dist: langchain-openai>=0.3.9; extra == "genai"
Dynamic: license-file
